{
	"name": "SourceDataset_amk",
	"properties": {
		"linkedServiceName": {
			"referenceName": "SriAzureBlobStorage",
			"type": "LinkedServiceReference"
		},
		"annotations": [],
		"type": "Json",
		"typeProperties": {
			"location": {
				"type": "AzureBlobStorageLocation",
				"fileName": "sample3.json",
				"container": "sri01"
			},
			"encodingName": "UTF-8"
		},
		"schema": {
			"type": "object",
			"properties": {
				"color": {
					"type": "string"
				},
				"value": {
					"type": "string"
				}
			}
		}
	}
}