{
	"$schema": "http://schema.management.azure.com/schemas/2015-01-01/deploymentTemplate.json#",
	"contentVersion": "1.0.0.0",
	"parameters": {
		"factoryName": {
			"type": "string",
			"metadata": "Data Factory name",
			"defaultValue": "Srini01"
		}
	},
	"variables": {
		"factoryId": "[concat('Microsoft.DataFactory/factories/', parameters('factoryName'))]"
	},
	"resources": [
		{
			"name": "[concat(parameters('factoryName'), '/CopyPipeline_amk')]",
			"type": "Microsoft.DataFactory/factories/pipelines",
			"apiVersion": "2018-06-01",
			"properties": {
				"activities": [
					{
						"name": "Copy_amk",
						"type": "Copy",
						"dependsOn": [],
						"policy": {
							"timeout": "7.00:00:00",
							"retry": 0,
							"retryIntervalInSeconds": 30,
							"secureOutput": false,
							"secureInput": false
						},
						"userProperties": [
							{
								"name": "Source",
								"value": "sri01//sample3.json"
							},
							{
								"name": "Destination",
								"value": "blob2-inc//Test_Json.json"
							}
						],
						"typeProperties": {
							"source": {
								"type": "JsonSource",
								"storeSettings": {
									"type": "AzureBlobStorageReadSettings",
									"recursive": true,
									"enablePartitionDiscovery": false
								},
								"formatSettings": {
									"type": "JsonReadSettings"
								}
							},
							"sink": {
								"type": "JsonSink",
								"storeSettings": {
									"type": "AzureBlobStorageWriteSettings"
								},
								"formatSettings": {
									"type": "JsonWriteSettings",
									"filePattern": "setOfObjects"
								}
							},
							"enableStaging": false,
							"validateDataConsistency": false,
							"translator": {
								"type": "TabularTranslator",
								"mappings": [
									{
										"source": {
											"path": "$['color']"
										},
										"sink": {
											"path": "$['color']"
										}
									},
									{
										"source": {
											"path": "$['value']"
										},
										"sink": {
											"path": "$['value']"
										}
									}
								]
							}
						},
						"inputs": [
							{
								"referenceName": "SourceDataset_amk",
								"type": "DatasetReference",
								"parameters": {}
							}
						],
						"outputs": [
							{
								"referenceName": "DestinationDataset_amk",
								"type": "DatasetReference",
								"parameters": {}
							}
						]
					}
				],
				"annotations": []
			},
			"dependsOn": []
		},
		{
			"name": "[concat(parameters('factoryName'), '/CopyPipeline_cvt')]",
			"type": "Microsoft.DataFactory/factories/pipelines",
			"apiVersion": "2018-06-01",
			"properties": {
				"activities": [
					{
						"name": "Copy_cvt",
						"type": "Copy",
						"dependsOn": [],
						"policy": {
							"timeout": "7.00:00:00",
							"retry": 0,
							"retryIntervalInSeconds": 30,
							"secureOutput": false,
							"secureInput": false
						},
						"userProperties": [
							{
								"name": "Source",
								"value": "sri01//sample1.json"
							},
							{
								"name": "Destination",
								"value": "sri01//Test_01.Json"
							}
						],
						"typeProperties": {
							"source": {
								"type": "JsonSource",
								"storeSettings": {
									"type": "AzureBlobStorageReadSettings",
									"recursive": true,
									"enablePartitionDiscovery": false
								},
								"formatSettings": {
									"type": "JsonReadSettings"
								}
							},
							"sink": {
								"type": "JsonSink",
								"storeSettings": {
									"type": "AzureBlobStorageWriteSettings"
								},
								"formatSettings": {
									"type": "JsonWriteSettings"
								}
							},
							"enableStaging": false,
							"enableSkipIncompatibleRow": false,
							"logSettings": {
								"enableCopyActivityLog": true,
								"copyActivityLogSettings": {
									"logLevel": "Warning",
									"enableReliableLogging": false
								},
								"logLocationSettings": {
									"linkedServiceName": {
										"referenceName": "SriAzureBlobStorage",
										"type": "LinkedServiceReference"
									},
									"path": "sri01"
								}
							},
							"translator": {
								"type": "TabularTranslator",
								"mappings": [
									{
										"source": {
											"path": "$['fruit']"
										},
										"sink": {
											"path": "$['fruit']"
										}
									},
									{
										"source": {
											"path": "$['size']"
										},
										"sink": {
											"path": "$['size']"
										}
									},
									{
										"source": {
											"path": "$['color']"
										},
										"sink": {
											"path": "$['color']"
										}
									}
								],
								"collectionReference": "$['phoneNumbers']"
							}
						},
						"inputs": [
							{
								"referenceName": "SourceDataset_cvt",
								"type": "DatasetReference",
								"parameters": {}
							}
						],
						"outputs": [
							{
								"referenceName": "SourceDataset_cvt",
								"type": "DatasetReference",
								"parameters": {}
							}
						]
					},
					{
						"name": "Copy data1",
						"type": "Copy",
						"dependsOn": [
							{
								"activity": "Copy_cvt",
								"dependencyConditions": [
									"Succeeded"
								]
							}
						],
						"policy": {
							"timeout": "7.00:00:00",
							"retry": 0,
							"retryIntervalInSeconds": 30,
							"secureOutput": false,
							"secureInput": false
						},
						"userProperties": [],
						"typeProperties": {
							"source": {
								"type": "JsonSource",
								"storeSettings": {
									"type": "AzureBlobStorageReadSettings",
									"recursive": true,
									"enablePartitionDiscovery": false
								},
								"formatSettings": {
									"type": "JsonReadSettings"
								}
							},
							"sink": {
								"type": "JsonSink",
								"storeSettings": {
									"type": "AzureBlobStorageWriteSettings"
								},
								"formatSettings": {
									"type": "JsonWriteSettings"
								}
							},
							"enableStaging": false,
							"translator": {
								"type": "TabularTranslator",
								"mappings": [
									{
										"source": {
											"path": "$['fruit']"
										},
										"sink": {
											"path": "$['fruit']"
										}
									},
									{
										"source": {
											"path": "$['size']"
										},
										"sink": {
											"path": "$['size']"
										}
									},
									{
										"source": {
											"path": "$['color']"
										},
										"sink": {
											"path": "$['color']"
										}
									}
								]
							}
						},
						"inputs": [
							{
								"referenceName": "Json1",
								"type": "DatasetReference",
								"parameters": {}
							}
						],
						"outputs": [
							{
								"referenceName": "Json1",
								"type": "DatasetReference",
								"parameters": {}
							}
						]
					}
				],
				"annotations": [],
				"lastPublishTime": "2021-07-08T18:16:13Z"
			},
			"dependsOn": []
		},
		{
			"name": "[concat(parameters('factoryName'), '/PL_blob2DataLake')]",
			"type": "Microsoft.DataFactory/factories/pipelines",
			"apiVersion": "2018-06-01",
			"properties": {
				"activities": [
					{
						"name": "Copy data1",
						"type": "Copy",
						"dependsOn": [],
						"policy": {
							"timeout": "7.00:00:00",
							"retry": 0,
							"retryIntervalInSeconds": 30,
							"secureOutput": false,
							"secureInput": false
						},
						"userProperties": [],
						"typeProperties": {
							"source": {
								"type": "JsonSource",
								"storeSettings": {
									"type": "AzureBlobStorageReadSettings",
									"recursive": true,
									"enablePartitionDiscovery": false
								},
								"formatSettings": {
									"type": "JsonReadSettings"
								}
							},
							"sink": {
								"type": "JsonSink",
								"storeSettings": {
									"type": "AzureBlobStorageWriteSettings"
								},
								"formatSettings": {
									"type": "JsonWriteSettings"
								}
							},
							"enableStaging": false
						},
						"inputs": [
							{
								"referenceName": "Json4",
								"type": "DatasetReference",
								"parameters": {}
							}
						],
						"outputs": [
							{
								"referenceName": "Json4",
								"type": "DatasetReference",
								"parameters": {}
							}
						]
					},
					{
						"name": "Copy data2",
						"type": "Copy",
						"dependsOn": [
							{
								"activity": "Copy data1",
								"dependencyConditions": [
									"Succeeded"
								]
							}
						],
						"policy": {
							"timeout": "7.00:00:00",
							"retry": 0,
							"retryIntervalInSeconds": 30,
							"secureOutput": false,
							"secureInput": false
						},
						"userProperties": [],
						"typeProperties": {
							"source": {
								"type": "JsonSource",
								"storeSettings": {
									"type": "AzureDataLakeStoreReadSettings",
									"recursive": true,
									"enablePartitionDiscovery": false
								},
								"formatSettings": {
									"type": "JsonReadSettings"
								}
							},
							"sink": {
								"type": "JsonSink",
								"storeSettings": {
									"type": "AzureDataLakeStoreWriteSettings"
								},
								"formatSettings": {
									"type": "JsonWriteSettings"
								}
							},
							"enableStaging": false
						},
						"inputs": [
							{
								"referenceName": "Json5",
								"type": "DatasetReference",
								"parameters": {}
							}
						],
						"outputs": [
							{
								"referenceName": "Json6",
								"type": "DatasetReference",
								"parameters": {}
							}
						]
					}
				],
				"annotations": []
			},
			"dependsOn": []
		}
	]
}